<annotation>
	<folder></folder>
	<filename>5889359290_6f1333e7b8_b_jpg.rf.65a7edeb63b1247da14509892287a0cb.jpg</filename>
	<path>5889359290_6f1333e7b8_b_jpg.rf.65a7edeb63b1247da14509892287a0cb.jpg</path>
	<source>
		<database>roboflow.ai</database>
	</source>
	<size>
		<width>640</width>
		<height>640</height>
		<depth>3</depth>
	</size>
	<segmented>0</segmented>
	<object>
		<name>otter</name>
		<pose>Unspecified</pose>
		<truncated>0</truncated>
		<difficult>0</difficult>
		<occluded>0</occluded>
		<bndbox>
			<xmin>220</xmin>
			<xmax>591</xmax>
			<ymin>203</ymin>
			<ymax>489</ymax>
		</bndbox>
	</object>
</annotation>
